actioncable_client/__init__.py
actioncable_client/action_base_channel.py
actioncable_client/connection.py
actioncable_client/message.py
actioncable_client/storage.py
actioncable_client/subscription.py
actioncable_client-0.3.0.dist-info/METADATA
actioncable_client-0.3.0.dist-info/WHEEL
actioncable_client-0.3.0.dist-info/licenses/LICENSE
actioncable_client-0.3.0.dist-info/RECORD
