Metadata-Version: 2.3
Name: actioncable_client
Version: 0.3.0
Summary: ActionCable Client for Python 3
Project-URL: Homepage, https://gitlab.com/liant-sasu/actioncable-client
Project-URL: Issues, https://gitlab.com/liant-sasu/actioncable-client/-/issues
Author-email: Tobias Feistmantl <tobias@myhome-automations.com>, Roland Laurès <roland@liant.dev>
License-File: LICENSE
Classifier: License :: OSI Approved :: MIT License
Classifier: Operating System :: OS Independent
Classifier: Programming Language :: Python :: 3
Classifier: Programming Language :: Python :: 3.9
Classifier: Programming Language :: Python :: 3.10
Classifier: Programming Language :: Python :: 3.11
Classifier: Programming Language :: Python :: 3.12
Requires-Python: >=3.9
